torch_ext/__init__.py
torch_ext/private.py
torch_ext/torch_ext.py
torch_ext/image/__init__.py
torch_ext/nn/__init__.py
torch_ext/nn/buffer.py
torch_ext/nn/buffer.pyi
torch_extension-0.0.1.3.9.dist-info/LICENSE
torch_extension-0.0.1.3.9.dist-info/METADATA
torch_extension-0.0.1.3.9.dist-info/WHEEL
torch_extension-0.0.1.3.9.dist-info/top_level.txt
torch_extension-0.0.1.3.9.dist-info/RECORD
