Metadata-Version: 2.1
Name: torch_extension
Version: 0.0.1.3.9
Summary: This Python module provides a collection of utility functions designed for advanced tensor manipulation using PyTorch. It includes functions for applying operations along specific dimensions, mapping values to new ranges, and generating linearly spaced tensors, among others.
Author-email: Caewinix <Caewinix@yeah.net>
Project-URL: Homepage, https://github.com/Caewinix/torch_extension
Project-URL: Bug Tracker, https://github.com/Caewinix/torch_extension/issues
Classifier: Programming Language :: Python :: 3
Classifier: License :: OSI Approved :: MIT License
Classifier: Operating System :: OS Independent
Requires-Python: >=3.7
License-File: LICENSE
Requires-Dist: torch >=1.6.0
Requires-Dist: numpy
Requires-Dist: array-like-generic
Requires-Dist: pyreflex
